Workbook
Name qtde_anos: APP!$D$20:$D$20
Name qtde_mensal: APP!$D$21:$D$21
Name rendimento_carteira: APP!$D$13:$D$13
Name sugestao: APP!$D$14:$D$14
Name sugestao_investimento: APP!$D$14:$D$14

Sheet APP
B11: CONFIGURAÇÕES
B12: Salário | D12: 2200
B13: Rendimento da carteira | D13: 0.006
B14: Sugestão de Investimento (30%) | D14: =30*D12/100 -> 660
B18: Investimento mensal
B19: Quanto investir por mês? | D19: 200
B20: Por quantos anos? | D20: 5
B21: Taxa de rendimento mensal | D21: 0.01079
B22: Patrimônio acumulado? | D22: =FV(D21,D20*12,D19*-1) -> 16755.383
B23: Dividendo mensais? | D23: =D22*$D$13 -> 100.5323
B26: Cenários | D26: Dividendo
A27: 2 | B27: Quanto em 2 anos? | C27: =FV($D$21,$A27*12,$D$19*-1) -> 5445.5255 | D27: =C27*$D$13 -> 32.673153
A28: 5 | B28: Quanto em 5 anos? | C28: =FV($D$21,$A28*12,$D$19*-1) -> 16755.383 | D28: =C28*$D$13 -> 100.5323
A29: 10 | B29: Quanto em 10 anos? | C29: =FV($D$21,$A29*12,$D$19*-1) -> 48656.843 | D29: =C29*$D$13 -> 291.94106
A30: 20 | B30: Quanto em 20 anos? | C30: =FV($D$21,$A30*12,$D$19*-1) -> 225039.68 | D30: =C30*$D$13 -> 1350.2381
A31: 30 | B31: Quanto em 30 anos? | C31: =FV($D$21,$A31*12,$D$19*-1) -> 864433.93 | D31: =C31*$D$13 -> 5186.6036
B36: PERFIL | C36: CONSERVADOR
B37: VALOR A SER INVESTIDO POR MÊS | C37: =D19 -> 200
B40: TIPO DE FII | C40: Percentual sugerido | D40: Valores
B41: PAPEL | C41: =VLOOKUP($C$36&"-"&B41,Planilha2!$B:$E,4,FALSE) -> 0.5 | D41: =$C$37*C41 -> 100
B42: TIJOLO | C42: =VLOOKUP($C$36&"-"&B42,Planilha2!$B:$E,4,FALSE) -> 0.1 | D42: =$C$37*C42 -> 20
B43: HÍBRIDO | C43: =VLOOKUP($C$36&"-"&B43,Planilha2!$B:$E,4,FALSE) -> 0.05 | D43: =$C$37*C43 -> 10
B44: FOFs | C44: =VLOOKUP($C$36&"-"&B44,Planilha2!$B:$E,4,FALSE) -> 0.05 | D44: =$C$37*C44 -> 10
B45: DESENVOLVIMENTO | C45: =VLOOKUP($C$36&"-"&B45,Planilha2!$B:$E,4,FALSE) -> 0.2 | D45: =$C$37*C45 -> 40
B46: HOTELARIA | C46: =VLOOKUP($C$36&"-"&B46,Planilha2!$B:$E,4,FALSE) -> 0.1 | D46: =$C$37*C46 -> 20
B47: VALOR TOTAL | D47: =SUM(D41:D46) -> 200

Sheet Planilha2
B4: CHAVE | C4: PERFIL | D4: TIPO DE FIL | E4: %
B5: =C5&"-"&D5 -> AGRESSIVO-PAPEL | C5: AGRESSIVO | D5: PAPEL | E5: 0.3 | H5: %
B6: =C6&"-"&D6 -> AGRESSIVO-TIJOLO | C6: AGRESSIVO | D6: TIJOLO | E6: 0.5 | G6: MODERADO-TIJOLO | H6: =VLOOKUP(G6,$B:$E,4,FALSE) -> 0.35
B7: =C7&"-"&D7 -> AGRESSIVO-HÍBRIDO | C7: AGRESSIVO | D7: HÍBRIDO | E7: 0.1
B8: =C8&"-"&D8 -> AGRESSIVO-FOFs | C8: AGRESSIVO | D8: FOFs | E8: 0.1
B9: =C9&"-"&D9 -> AGRESSIVO-DESENVOLVIMENTO | C9: AGRESSIVO | D9: DESENVOLVIMENTO | E9: 0
B10: =C10&"-"&D10 -> AGRESSIVO-HOTELARIA | C10: AGRESSIVO | D10: HOTELARIA | E10: 0
B11: =C11&"-"&D11 -> MODERADO-PAPEL | C11: MODERADO | D11: PAPEL | E11: 0.32
B12: =C12&"-"&D12 -> MODERADO-TIJOLO | C12: MODERADO | D12: TIJOLO | E12: 0.35
B13: =C13&"-"&D13 -> MODERADO-HÍBRIDO | C13: MODERADO | D13: HÍBRIDO | E13: 0.08
B14: =C14&"-"&D14 -> MODERADO-FOFs | C14: MODERADO | D14: FOFs | E14: 0.05
B15: =C15&"-"&D15 -> MODERADO-DESENVOLVIMENTO | C15: MODERADO | D15: DESENVOLVIMENTO | E15: 0.1
B16: =C16&"-"&D16 -> MODERADO-HOTELARIA | C16: MODERADO | D16: HOTELARIA | E16: 0.1
B17: =C17&"-"&D17 -> CONSERVADOR-PAPEL | C17: CONSERVADOR | D17: PAPEL | E17: 0.5
B18: =C18&"-"&D18 -> CONSERVADOR-TIJOLO | C18: CONSERVADOR | D18: TIJOLO | E18: 0.1
... B22: =C22&"-"&D22 -> CONSERVADOR-HOTELARIA | C22: CONSERVADOR | D22: HOTELARIA | E22: 0.1
